__init__.py
animal.py
not_very_useful_animal-1.2.0.dist-info/WHEEL
not_very_useful_animal-1.2.0.dist-info/METADATA
not_very_useful_animal-1.2.0.dist-info/RECORD
