Metadata-Version: 2.1
Name: not-very-useful-animal
Version: 1.2.0
Summary: a not very useful animal
Author: Fatemejahanni
Requires-Python: >=3.9,<4.0
Classifier: Programming Language :: Python :: 3
Classifier: Programming Language :: Python :: 3.10
Classifier: Programming Language :: Python :: 3.9
